.gitignore
LICENSE.txt
README.md
requirements-dev.txt
setup.py
.github/issue_template.md
.github/pull_request_template.md
cherrytree/__init__.py
cherrytree/branch.py
cherrytree/classes.py
cherrytree/github_utils.py
cherrytree.egg-info/PKG-INFO
cherrytree.egg-info/SOURCES.txt
cherrytree.egg-info/dependency_links.txt
cherrytree.egg-info/not-zip-safe
cherrytree.egg-info/requires.txt
cherrytree.egg-info/top_level.txt
cherrytree/bin/cherrytree