Metadata-Version: 2.1
Name: cherrytree
Version: 2.0.1
Summary: A build tool to pick cherry, bake release branches, and power label-driven development
Home-page: https://github.com/apache-superset/cherrytree
Author: Maxime Beauchemin
Author-email: maximebeauchemin@gmail.com
License: UNKNOWN
Download-URL: https://github.com/apache-superset/cherrytree/tarball/2.0.1
Platform: UNKNOWN
Classifier: Programming Language :: Python :: 3.6
Classifier: Programming Language :: Python :: 3.7
Classifier: Programming Language :: Python :: 3.8
Classifier: Programming Language :: Python :: 3.9
